llama_index/extractors/relik/__init__.py
llama_index/extractors/relik/base.py
llama_index_extractors_relik-0.4.0.dist-info/METADATA
llama_index_extractors_relik-0.4.0.dist-info/WHEEL
llama_index_extractors_relik-0.4.0.dist-info/licenses/LICENSE
llama_index_extractors_relik-0.4.0.dist-info/RECORD
