Metadata-Version: 2.4
Name: llama-index-extractors-relik
Version: 0.4.0
Summary: llama-index extractors relik integration
Author-email: Your Name <you@example.com>
License-Expression: MIT
License-File: LICENSE
Requires-Python: <4,>=3.10
Requires-Dist: huggingface-hub>=0.23.0
Requires-Dist: llama-index-core<0.14,>=0.13.0
Requires-Dist: relik<2,>=1.0.3
Requires-Dist: spacy
